keyweave/__init__.py
keyweave/_hook/__init__.py
keyweave/_util/func.py
keyweave/_util/logging.py
keyweave/bindings/__init__.py
keyweave/commanding/__init__.py
keyweave/hotkey/__init__.py
keyweave/interception/__init__.py
keyweave/key/__init__.py
keyweave/key_types/__init__.py
keyweave/layout/__init__.py
keyweave/layout/_layout.py
keyweave/layout/_layout_class.py
keyweave/layout/_print_layout.py
keyweave/layout/print.py
keyweave/print/based_int.py
keyweave/print/escape.py
keyweave/print/style.py
keyweave/print/yaml.py
keyweave/py.typed
keyweave/scheduling/__init__.py
keyweave/shorthand.py
keyweave/util/dict.py
keyweave/util/event_loop.py
keyweave/util/input.py
keyweave/util/reflect.py
keyweave-0.18.6.dist-info/METADATA
keyweave-0.18.6.dist-info/WHEEL
keyweave-0.18.6.dist-info/licenses/LICENSE.md
keyweave-0.18.6.dist-info/RECORD
