Metadata-Version: 2.4
Name: keyweave
Version: 0.18.6
Summary: Framework for defining global hotkeys.
License: MIT
License-File: LICENSE.md
Author: GregRos
Author-email: gregros@gregros.dev
Requires-Python: >=3.13,<3.15
Classifier: License :: OSI Approved :: MIT License
Classifier: Programming Language :: Python :: 3
Classifier: Programming Language :: Python :: 3.13
Classifier: Programming Language :: Python :: 3.14
Requires-Dist: keyboard (>=0.13.5,<0.14.0)
Requires-Dist: mouse (>=0.7.1,<0.8.0) ; sys_platform != "win32"
Requires-Dist: pyee (>=13.0.0,<14.0.0)
Requires-Dist: python-baseconv (>=1.2.2,<2.0.0)
Requires-Dist: pywin32 (>=311,<312) ; sys_platform == "win32"
Requires-Dist: pyyaml (>=6.0.3,<7.0.0)
Requires-Dist: termcolor (>=3.1.0,<4.0.0)
Project-URL: Homepage, https://github.com/GregRos/keyweave
